canonmap/__init__.py
canonmap/cli.py
canonmap/exceptions.py
canonmap/logger.py
canonmap/_example_usage/.env.example
canonmap/_example_usage/__init__.py
canonmap/_example_usage/app/__init__.py
canonmap/_example_usage/app/context.py
canonmap/_example_usage/app/main.py
canonmap/_example_usage/app/validation.py
canonmap/_example_usage/app/routes/db_routes.py
canonmap/_example_usage/app/routes/db_routes_low_level.py
canonmap/_example_usage/app/routes/entity_routes.py
canonmap/connectors/__init__.py
canonmap/connectors/mysql_connector/__init__.py
canonmap/connectors/mysql_connector/config.py
canonmap/connectors/mysql_connector/connector.py
canonmap/connectors/mysql_connector/db_client.py
canonmap/connectors/mysql_connector/models.py
canonmap/connectors/mysql_connector/services/__init__.py
canonmap/connectors/mysql_connector/services/constraint_service.py
canonmap/connectors/mysql_connector/services/field_service.py
canonmap/connectors/mysql_connector/services/helper_fields_service.py
canonmap/connectors/mysql_connector/services/import_table_service.py
canonmap/connectors/mysql_connector/services/schema_service.py
canonmap/connectors/mysql_connector/utils/__init__.py
canonmap/connectors/mysql_connector/utils/db_metadata.py
canonmap/connectors/mysql_connector/utils/dml.py
canonmap/connectors/mysql_connector/utils/paging.py
canonmap/connectors/mysql_connector/utils/retry.py
canonmap/connectors/mysql_connector/utils/sql_identifiers.py
canonmap/connectors/mysql_connector/utils/transforms.py
canonmap/connectors/mysql_connector/utils/type_inference.py
canonmap/mapping/__init__.py
canonmap/mapping/mapping_pipeline.py
canonmap/mapping/models.py
canonmap/mapping/utils/__init__.py
canonmap/mapping/utils/blocking.py
canonmap/mapping/utils/normalize.py
canonmap/mapping/utils/prefilter_helpers.py
canonmap/mapping/utils/scoring.py
canonmap-1.0.2.dist-info/METADATA
canonmap-1.0.2.dist-info/WHEEL
canonmap-1.0.2.dist-info/entry_points.txt
canonmap-1.0.2.dist-info/licenses/LICENSE
canonmap-1.0.2.dist-info/RECORD
